centralogger/__init__.py
centralogger/telegram_handler.py
centralogger-0.0.1.dist-info/LICENSE
centralogger-0.0.1.dist-info/METADATA
centralogger-0.0.1.dist-info/WHEEL
centralogger-0.0.1.dist-info/top_level.txt
centralogger-0.0.1.dist-info/RECORD
