Metadata-Version: 2.1
Name: centralogger
Version: 0.0.1
Summary: Log handler to deliver logs to multiple end points
Home-page: https://github.com/reevoremo/centralogger
Author: Behan Remoshan BENET RUBAN
Author-email: reevoremo@gmail.com
License: UNKNOWN
Platform: UNKNOWN
Classifier: Programming Language :: Python :: 3
Classifier: License :: OSI Approved :: MIT License
Classifier: Operating System :: OS Independent
Requires-Python: >=3.6
